orders/__init__.py
orders/pyfs.py
Algomojo_kambala-0.1.dist-info/METADATA
Algomojo_kambala-0.1.dist-info/WHEEL
Algomojo_kambala-0.1.dist-info/top_level.txt
Algomojo_kambala-0.1.dist-info/RECORD
