Metadata-Version: 2.1
Name: Algomojo-kambala
Version: 0.1
Summary: A functional python wrapper for algomojo trading api
Home-page: https://algomojo.com/docs/python
Author: Algomojo
Author-email: support@algomojo.com
License: MIT
Platform: UNKNOWN
Classifier: License :: OSI Approved :: MIT License
Classifier: Programming Language :: Python
Classifier: Programming Language :: Python :: 2
Classifier: Programming Language :: Python :: 3
Requires-Dist: requests
